MANIFEST.in
README.md
README.rst
setup.py
pyfrank.egg-info/PKG-INFO
pyfrank.egg-info/SOURCES.txt
pyfrank.egg-info/dependency_links.txt
pyfrank.egg-info/entry_points.txt
pyfrank.egg-info/not-zip-safe
pyfrank.egg-info/top_level.txt
src/__init__.py
src/exceptions.py
src/frank.py