Metadata-Version: 1.1
Name: pyfrank
Version: 0.2.8
Summary: python binding for iOS automation using frank.
Home-page: https://github.com/everythingme/pyfrank
Author: Daniel Ben-Zvi
Author-email: daniel@doit9.com
License: BSD
Keywords: python frank pyfrank frankly ios qa automation robot testing
Platform: UNKNOWN
Classifier: Development Status :: 4 - Beta
Classifier: License :: OSI Approved :: BSD License
Classifier: Intended Audience :: Developers
Classifier: Programming Language :: Python :: 2.7
Classifier: Topic :: Software Development :: Testing
